src/main.py
hangovergames_assetgen-0.1.0.data/data/LICENSE
hangovergames_assetgen-0.1.0.data/data/README.md
hangovergames_assetgen-0.1.0.dist-info/METADATA
hangovergames_assetgen-0.1.0.dist-info/WHEEL
hangovergames_assetgen-0.1.0.dist-info/entry_points.txt
hangovergames_assetgen-0.1.0.dist-info/licenses/LICENSE
hangovergames_assetgen-0.1.0.dist-info/RECORD
