Metadata-Version: 2.4
Name: hangovergames-assetgen
Version: 0.1.0
Summary: Generate game graphics using OpenAI's image generation APIs
Project-URL: Homepage, https://github.com/hangovergames/assetgen
Project-URL: Repository, https://github.com/hangovergames/assetgen.git
Author-email: Hangover Games <info@hangovergames.com>
License-Expression: MIT
License-File: LICENSE
Classifier: Development Status :: 4 - Beta
Classifier: Intended Audience :: Developers
Classifier: License :: OSI Approved :: MIT License
Classifier: Programming Language :: Python :: 3
Classifier: Programming Language :: Python :: 3.8
Classifier: Programming Language :: Python :: 3.9
Classifier: Programming Language :: Python :: 3.10
Classifier: Programming Language :: Python :: 3.11
Classifier: Topic :: Games/Entertainment
Classifier: Topic :: Software Development :: Libraries :: Python Modules
Requires-Python: >=3.8
Requires-Dist: requests>=2.31.0
